ha_desktop_remote/__init__.py
ha_desktop_remote/main.py
ha_desktop_remote/remote_manager.py
ha_desktop_remote/remote_window.py
ha_desktop_remote/remote_wizard.py
ha_desktop_remote-1.0.4.dist-info/licenses/LICENSE
ha_desktop_remote-1.0.4.dist-info/METADATA
ha_desktop_remote-1.0.4.dist-info/WHEEL
ha_desktop_remote-1.0.4.dist-info/entry_points.txt
ha_desktop_remote-1.0.4.dist-info/top_level.txt
ha_desktop_remote-1.0.4.dist-info/RECORD
