Metadata-Version: 2.4
Name: ha-desktop-remote
Version: 1.0.4
Summary: Desktop remote control application for Home Assistant
Author-email: David Markey <david@dmarkey.com>
License: MIT License
Project-URL: Homepage, https://github.com/dmarkey/ha-desktop-remote
Project-URL: Repository, https://github.com/dmarkey/ha-desktop-remote
Project-URL: Issues, https://github.com/dmarkey/ha-desktop-remote/issues
Project-URL: Documentation, https://github.com/dmarkey/ha-desktop-remote#readme
Keywords: home-assistant,remote,control,desktop,gui,qt,pyside6,automation,smart-home
Classifier: Development Status :: 5 - Production/Stable
Classifier: Intended Audience :: End Users/Desktop
Classifier: Topic :: Home Automation
Classifier: Topic :: Multimedia
Classifier: Topic :: System :: Hardware
Classifier: License :: OSI Approved :: MIT License
Classifier: Programming Language :: Python :: 3
Classifier: Programming Language :: Python :: 3.8
Classifier: Programming Language :: Python :: 3.9
Classifier: Programming Language :: Python :: 3.10
Classifier: Programming Language :: Python :: 3.11
Classifier: Programming Language :: Python :: 3.12
Classifier: Operating System :: OS Independent
Classifier: Environment :: X11 Applications :: Qt
Classifier: Environment :: Win32 (MS Windows)
Classifier: Environment :: MacOS X
Requires-Python: >=3.8
License-File: LICENSE
Requires-Dist: PySide6>=6.0.0
Requires-Dist: requests>=2.25.0
Provides-Extra: dev
Requires-Dist: pytest>=6.0; extra == "dev"
Requires-Dist: pytest-qt>=4.0; extra == "dev"
Requires-Dist: black>=22.0; extra == "dev"
Requires-Dist: flake8>=4.0; extra == "dev"
Requires-Dist: mypy>=0.900; extra == "dev"
Dynamic: license-file
